<Properties StartupConfiguration="{229CB5D4-0E25-4FE3-B3D5-D73989F6B4DE}|Default">
  <MonoDevelop.Ide.Workbench>
    <Pads>
      <Pad Id="ProjectPad">
        <State name="__root__">
          <Node name="GameDemo" expanded="True">
            <Node name="GameDemo" expanded="True">
              <Node name="Dependencies" expanded="True" />
              <Node name="Animations" expanded="True" />
              <Node name="Characters" expanded="True" />
              <Node name="Content" expanded="True">
                <Node name="Characters" expanded="True">
                  <Node name="lphoenix" expanded="True" />
                  <Node name="redgeworth" expanded="True" />
                </Node>
              </Node>
              <Node name="Dialogue" expanded="True" />
              <Node name="Effects" expanded="True">
                <Node name="Audio.cs" selected="True" />
              </Node>
              <Node name="Events" expanded="True" />
              <Node name="Locations" expanded="True" />
              <Node name="Managers" expanded="True" />
            </Node>
          </Node>
        </State>
      </Pad>
    </Pads>
  </MonoDevelop.Ide.Workbench>
  <MonoDevelop.Ide.DebuggingService.PinnedWatches />
  <MonoDevelop.Ide.Workspace ActiveConfiguration="Debug" />
  <MonoDevelop.Ide.DebuggingService.Breakpoints>
    <BreakpointStore />
  </MonoDevelop.Ide.DebuggingService.Breakpoints>
  <MultiItemStartupConfigurations />
  <MonoDevelop.Ide.ItemProperties.GameDemo PreferredExecutionTarget="MonoDevelop.Default" />
</Properties>